iec62056_21/__init__.py
iec62056_21/client.py
iec62056_21/constants.py
iec62056_21/exceptions.py
iec62056_21/lis200.py
iec62056_21/messages.py
iec62056_21/meter.py
iec62056_21/transports.py
iec62056_21/utils.py
iec62056_21-0.0.2.dist-info/LICENSE.txt
iec62056_21-0.0.2.dist-info/METADATA
iec62056_21-0.0.2.dist-info/WHEEL
iec62056_21-0.0.2.dist-info/top_level.txt
iec62056_21-0.0.2.dist-info/RECORD
