Metadata-Version: 2.1
Name: iec62056-21
Version: 0.0.2
Summary: A Python library for IEC62056-21, Local Data Readout of Energy Meters. Former IEC1107
Home-page: https://github.com/pwitab/iec62056-21
Author: Henrik Palmlund Wahlgren @ Palmlund Wahlgren Innovative Technology AB
Author-email: henrik@pwit.se
License: BSD-3-Clause
Keywords: metering,amr,iec62056-21
Platform: UNKNOWN
Requires-Python: ~=3.6
Requires-Dist: attrs (>=19.1.0)
Requires-Dist: pyserial (>=3.4)
